rmediator/__init__.py
rmediator/mediator.py
rmediator/decorators/__init__.py
rmediator/decorators/request.py
rmediator/decorators/request_handler.py
rmediator/types/__init__.py
rmediator/types/request.py
rmediator/types/request_handler.py
rmediator-0.2.7.dist-info/LICENSE
rmediator-0.2.7.dist-info/METADATA
rmediator-0.2.7.dist-info/WHEEL
rmediator-0.2.7.dist-info/top_level.txt
rmediator-0.2.7.dist-info/RECORD
