Metadata-Version: 2.2
Name: rmediator
Version: 0.2.7
Summary: Request Mediator PyPI (Python Package Index) Package
Home-page: https://github.com/ffekirnew/rmediator
Author: Fikernew Birhanu
Author-email: fikernew.birhanu.waju@gmail.com
Project-URL: Documentation, https://github.com/ffekirnew/rmediator
Project-URL: Bug Reports, https://github.com/ffekirnew/rmediator/issues
Project-URL: Source Code, https://github.com/ffekirnew/rmediator
Keywords: rmediator,pypi,package
Classifier: Development Status :: 5 - Production/Stable
Classifier: Intended Audience :: Developers
Classifier: Topic :: Software Development :: Build Tools
Classifier: Programming Language :: Python :: 3
Classifier: Programming Language :: Python :: 3.11
Classifier: Programming Language :: Python :: 3 :: Only
Classifier: License :: OSI Approved :: MIT License
Classifier: Operating System :: OS Independent
Requires-Python: >=3.6
License-File: LICENSE
Provides-Extra: dev
Requires-Dist: check-manifest; extra == "dev"
Dynamic: author
Dynamic: author-email
Dynamic: classifier
Dynamic: description
Dynamic: description-content-type
Dynamic: home-page
Dynamic: keywords
Dynamic: project-url
Dynamic: provides-extra
Dynamic: requires-python
Dynamic: summary
